cyanobyte/__init__.py
cyanobyte/codegen.py
cyanobyte/validator.py
cyanobyte-0.0.1.dist-info/LICENSE
cyanobyte-0.0.1.dist-info/METADATA
cyanobyte-0.0.1.dist-info/WHEEL
cyanobyte-0.0.1.dist-info/entry_points.txt
cyanobyte-0.0.1.dist-info/top_level.txt
cyanobyte-0.0.1.dist-info/RECORD
