Metadata-Version: 2.1
Name: cyanobyte
Version: 0.0.1
Summary: A package that generates library files for a peripheral given an intermediary layer (YAML files)
Home-page: https://github.com/google/cyanobyte
Author: Google Inc.
Author-email: fleker@google.com
License: UNKNOWN
Platform: UNKNOWN
Classifier: Programming Language :: Python :: 3
Classifier: License :: OSI Approved :: Apache Software License
Classifier: Operating System :: OS Independent
Requires-Python: >=3.0
Requires-Dist: click
Requires-Dist: pylint
Requires-Dist: pyyaml
Requires-Dist: Jinja2
Requires-Dist: jsonschema
Requires-Dist: importlib-metadata
Requires-Dist: pathlib2
